CHANGELOG.md
hobart/__init__.py
hobart/_core.py
hobart/_internal.py
hobart/_validation.py
hobart-1.1.1.dist-info/LICENSE
hobart-1.1.1.dist-info/WHEEL
hobart-1.1.1.dist-info/METADATA
hobart-1.1.1.dist-info/RECORD
